{"RECORDS":
[{"Irank": "1", "MovieName": "战狼2", "BoxOffice": "4240060000.0", "SumBoxOffice": "4240060000.0", "Director": "吴京", "Genre1": "动作", "Genre2": "-", "Genre3": "-", "CAST1": "吴京", "CAST2": "弗兰克·格里罗", "CAST3": "吴刚", "CAST4": "张翰", "CAST5": "卢靖姗"},
{"Irank": "2", "MovieName": "三生三世十里桃花", "BoxOffice": "534188000.0", "SumBoxOffice": "534188000.0", "Director": "赵小丁", "Genre1": "爱情", "Genre2": "奇幻", "Genre3": "-", "CAST1": "刘亦菲", "CAST2": "杨洋", "CAST3": "罗晋", "CAST4": "严屹宽", "CAST5": "李纯"},
{"Irank": "3", "MovieName": "杀破狼·贪狼", "BoxOffice": "490867000.0", "SumBoxOffice": "490867000.0", "Director": "叶伟信", "Genre1": "剧情", "Genre2": "动作", "Genre3": "-", "CAST1": "古天乐", "CAST2": "吴樾", "CAST3": "托尼·贾", "CAST4": "林家栋", "CAST5": "克里斯·柯林斯"},
{"Irank": "4", "MovieName": "星际特工：千星之城", "BoxOffice": "341474000.0", "SumBoxOffice": "341474000.0", "Director": "吕克·贝松", "Genre1": "动作", "Genre2": "科幻", "Genre3": "冒险", "CAST1": "戴恩·德哈恩", "CAST2": "卡拉·迪瓦伊", "CAST3": "克里夫·欧文", "CAST4": "蕾哈娜", "CAST5": "伊桑·霍克"},
{"Irank": "5", "MovieName": "心理罪", "BoxOffice": "290121000.0", "SumBoxOffice": "290121000.0", "Director": "谢东燊", "Genre1": "动作", "Genre2": "悬疑", "Genre3": "犯罪", "CAST1": "廖凡", "CAST2": "李易峰", "CAST3": "万茜", "CAST4": "李纯", "CAST5": "张国柱"},
{"Irank": "6", "MovieName": "侠盗联盟", "BoxOffice": "236523000.0", "SumBoxOffice": "236523000.0", "Director": "冯德伦", "Genre1": "动作", "Genre2": "冒险", "Genre3": "-", "CAST1": "刘德华", "CAST2": "舒淇", "CAST3": "张静初", "CAST4": "杨祐宁", "CAST5": "让·雷诺"},
{"Irank": "7", "MovieName": "二十二", "BoxOffice": "168251000.0", "SumBoxOffice": "168251000.0", "Director": "郭柯", "Genre1": "纪录片", "Genre2": "-", "Genre3": "-", "CAST1": "-", "CAST2": "-", "CAST3": "-", "CAST4": "-", "CAST5": "-"},
{"Irank": "8", "MovieName": "建军大业", "BoxOffice": "158059000.0", "SumBoxOffice": "158059000.0", "Director": "刘伟强", "Genre1": "剧情", "Genre2": "历史", "Genre3": "-", "CAST1": "刘烨", "CAST2": "朱亚文", "CAST3": "黄志忠", "CAST4": "王景春", "CAST5": "欧豪"},
{"Irank": "9", "MovieName": "十万个冷笑话2", "BoxOffice": "125882000.0", "SumBoxOffice": "125882000.0", "Director": "卢恒宇", "Genre1": "喜剧", "Genre2": "动画", "Genre3": "奇幻", "CAST1": "山新", "CAST2": "郝祥海", "CAST3": "李姝洁", "CAST4": "藤新", "CAST5": "图特哈蒙"},
{"Irank": "10", "MovieName": "鲛珠传", "BoxOffice": "113410000.0", "SumBoxOffice": "113410000.0", "Director": "杨磊", "Genre1": "喜剧", "Genre2": "动作", "Genre3": "爱情", "CAST1": "王大陆", "CAST2": "张天爱", "CAST3": "任达华", "CAST4": "盛冠森", "CAST5": "王迅"},
{"Irank": "11", "MovieName": "赛车总动员3：极速挑战", "BoxOffice": "108839000.0", "SumBoxOffice": "108839000.0", "Director": "布莱恩·菲", "Genre1": "喜剧", "Genre2": "动画", "Genre3": "冒险", "CAST1": "欧文·威尔逊", "CAST2": "克里斯黛拉·阿朗索", "CAST3": "克里斯·库珀", "CAST4": "内森·菲利安", "CAST5": "王牌接线员拉里"},
{"Irank": "12", "MovieName": "极盗车神", "BoxOffice": "102263000.0", "SumBoxOffice": "102263000.0", "Director": "埃德加·赖特", "Genre1": "动作", "Genre2": "音乐", "Genre3": "犯罪", "CAST1": "安塞尔·艾尔高特", "CAST2": "凯文·史派西", "CAST3": "杰米·福克斯", "CAST4": "乔恩·哈姆", "CAST5": "艾莎·冈萨雷斯"},
{"Irank": "14", "MovieName": "破·局", "BoxOffice": "64194600.0", "SumBoxOffice": "64194600.0", "Director": "连奕琦", "Genre1": "动作", "Genre2": "犯罪", "Genre3": "-", "CAST1": "郭富城", "CAST2": "王千源", "CAST3": "刘涛", "CAST4": "余皑磊", "CAST5": "冯嘉怡"},
{"Irank": "15", "MovieName": "龙之战", "BoxOffice": "56248200.0", "SumBoxOffice": "56248200.0", "Director": "高峰", "Genre1": "动作", "Genre2": "历史", "Genre3": "战争", "CAST1": "刘佩琦", "CAST2": "曹云金", "CAST3": "罗昱焜", "CAST4": "李子雄", "CAST5": "-"},
{"Irank": "16", "MovieName": "地球：神奇的一天", "BoxOffice": "43777000.0", "SumBoxOffice": "43777000.0", "Director": "理查德·戴尔", "Genre1": "纪录片", "Genre2": "-", "Genre3": "-", "CAST1": "成龙", "CAST2": "罗伯特·雷德福", "CAST3": "黄子华", "CAST4": "佐佐木藏之介", "CAST5": "-"},
{"Irank": "17", "MovieName": "神偷奶爸3", "BoxOffice": "42849800.0", "SumBoxOffice": "42849800.0", "Director": "凯尔·巴尔达", "Genre1": "喜剧", "Genre2": "动画", "Genre3": "冒险", "CAST1": "史蒂夫·卡瑞尔", "CAST2": "克里斯汀·韦格", "CAST3": "崔·帕克", "CAST4": "米兰达·卡斯格拉夫", "CAST5": "达纳·盖尔"},
{"Irank": "18", "MovieName": "玩偶奇兵", "BoxOffice": "23615400.0", "SumBoxOffice": "23615400.0", "Director": "申宇", "Genre1": "动画", "Genre2": "奇幻", "Genre3": "冒险", "CAST1": "严丽祯", "CAST2": "李晔", "CAST3": "王衡", "CAST4": "李传缨", "CAST5": "李心仪"},
{"Irank": "19", "MovieName": "大耳朵图图之美食狂想曲", "BoxOffice": "17943500.0", "SumBoxOffice": "17943500.0", "Director": "速达", "Genre1": "喜剧", "Genre2": "动画", "Genre3": "冒险", "CAST1": "潘延", "CAST2": "范楚绒", "CAST3": "胡谦", "CAST4": "王衡", "CAST5": "李晔"},
{"Irank": "20", "MovieName": "血战湘江", "BoxOffice": "16563900.0", "SumBoxOffice": "16563900.0", "Director": "陈力", "Genre1": "历史", "Genre2": "战争", "Genre3": "-", "CAST1": "王霙", "CAST2": "徐箭", "CAST3": "董勇", "CAST4": "孙维民", "CAST5": "保剑锋"},
{"Irank": "21", "MovieName": "二次初恋", "BoxOffice": "12477100.0", "SumBoxOffice": "12477100.0", "Director": "戴玮", "Genre1": "喜剧", "Genre2": "爱情", "Genre3": "奇幻", "CAST1": "朱茵", "CAST2": "杜天皓", "CAST3": "黄征", "CAST4": "王志飞", "CAST5": "王嘉宁"},
{"Irank": "22", "MovieName": "我是马布里", "BoxOffice": "8742850.0", "SumBoxOffice": "8742850.0", "Director": "杨子", "Genre1": "剧情", "Genre2": "运动", "Genre3": "-", "CAST1": "斯蒂芬·马布里", "CAST2": "吴尊", "CAST3": "何冰", "CAST4": "郑秀妍", "CAST5": "王庆祥"},
{"Irank": "23", "MovieName": "闪光少女", "BoxOffice": "7952900.0", "SumBoxOffice": "7952900.0", "Director": "王冉", "Genre1": "喜剧", "Genre2": "音乐", "Genre3": "-", "CAST1": "徐璐", "CAST2": "彭昱畅", "CAST3": "刘泳希", "CAST4": "鲁照华", "CAST5": "韩忠羽"},
{"Irank": "26", "MovieName": "海边的曼彻斯特", "BoxOffice": "4970480.0", "SumBoxOffice": "4970480.0", "Director": "肯尼思·洛纳根", "Genre1": "剧情", "Genre2": "家庭", "Genre3": "-", "CAST1": "卡西·阿弗莱克", "CAST2": "卢卡斯·赫奇斯", "CAST3": "米歇尔·威廉姆斯", "CAST4": "C·J·威尔逊", "CAST5": "凯尔·钱德勒"},
{"Irank": "27", "MovieName": "黑白迷宫", "BoxOffice": "4839170.0", "SumBoxOffice": "4839170.0", "Director": "阚家伟", "Genre1": "剧情", "Genre2": "动作", "Genre3": "犯罪", "CAST1": "任达华", "CAST2": "陈小春", "CAST3": "伍允龙", "CAST4": "邱意浓", "CAST5": "张兆辉"},
{"Irank": "28", "MovieName": "悟空传", "BoxOffice": "3589480.0", "SumBoxOffice": "3589480.0", "Director": "郭子健", "Genre1": "剧情", "Genre2": "动作", "Genre3": "奇幻", "CAST1": "彭于晏", "CAST2": "倪妮", "CAST3": "余文乐", "CAST4": "俞飞鸿", "CAST5": "欧豪"},
{"Irank": "29", "MovieName": "大象林旺之一炮成名", "BoxOffice": "3258750.0", "SumBoxOffice": "3258750.0", "Director": "李涛歌", "Genre1": "动作", "Genre2": "动画", "Genre3": "战争", "CAST1": "宋晓宇", "CAST2": "李垚", "CAST3": "徐炜", "CAST4": "葛平", "CAST5": "张怀武"},
{"Irank": "30", "MovieName": "皮绳上的魂", "BoxOffice": "3162080.0", "SumBoxOffice": "3162080.0", "Director": "张杨", "Genre1": "剧情", "Genre2": "-", "Genre3": "-", "CAST1": "金巴", "CAST2": "曲尼次仁", "CAST3": "夏诺·扎西敦珠", "CAST4": "索朗尼玛", "CAST5": "益西旦增"},
{"Irank": "31", "MovieName": "敦刻尔克", "BoxOffice": "3093070.0", "SumBoxOffice": "3093070.0", "Director": "克里斯托弗·诺兰", "Genre1": "剧情", "Genre2": "历史", "Genre3": "战争", "CAST1": "菲恩·怀特海德", "CAST2": "汤姆·格林-卡尼", "CAST3": "杰克·劳登", "CAST4": "哈里·斯泰尔斯", "CAST5": "阿奈林·巴纳德"},
{"Irank": "32", "MovieName": "豆福传", "BoxOffice": "2545090.0", "SumBoxOffice": "2545090.0", "Director": "邹燚", "Genre1": "动画", "Genre2": "-", "Genre3": "-", "CAST1": "陈佩斯", "CAST2": "李立群", "CAST3": "季冠霖", "CAST4": "付博文", "CAST5": "-"},
{"Irank": "33", "MovieName": "恐怖毕业照2", "BoxOffice": "2049800.0", "SumBoxOffice": "2049800.0", "Director": "陆诗雨", "Genre1": "惊悚", "Genre2": "恐怖", "Genre3": "-", "CAST1": "陈圆", "CAST2": "刘俐儿", "CAST3": "宋伟", "CAST4": "聂晶磊", "CAST5": "柴子娣"},
{"Irank": "34", "MovieName": "父子雄兵", "BoxOffice": "1816360.0", "SumBoxOffice": "1816360.0", "Director": "袁卫东", "Genre1": "喜剧", "Genre2": "-", "Genre3": "-", "CAST1": "大鹏", "CAST2": "范伟", "CAST3": "张天爱", "CAST4": "乔杉", "CAST5": "邬君梅"},
{"Irank": "36", "MovieName": "大护法", "BoxOffice": "1373420.0", "SumBoxOffice": "1373420.0", "Director": "不思凡", "Genre1": "喜剧", "Genre2": "动画", "Genre3": "奇幻", "CAST1": "小连杀", "CAST2": "图特哈蒙", "CAST3": "金士杰", "CAST4": "幽舞越山", "CAST5": "李佳怡"},
{"Irank": "37", "MovieName": "阿唐奇遇", "BoxOffice": "1314870.0", "SumBoxOffice": "1314870.0", "Director": "王微", "Genre1": "动画", "Genre2": "奇幻", "Genre3": "冒险", "CAST1": "石磊", "CAST2": "原泽宇", "CAST3": "季冠霖", "CAST4": "洪晃", "CAST5": "米粒"},
{"Irank": "38", "MovieName": "我是谁的宝贝", "BoxOffice": "1112960.0", "SumBoxOffice": "1112960.0", "Director": "李南", "Genre1": "剧情", "Genre2": "家庭", "Genre3": "犯罪", "CAST1": "郑国霖", "CAST2": "程皓枫", "CAST3": "华少", "CAST4": "蒋小涵", "CAST5": "许绍雄"},
{"Irank": "39", "MovieName": "诡井", "BoxOffice": "1033130.0", "SumBoxOffice": "1033130.0", "Director": "常杨", "Genre1": "惊悚", "Genre2": "恐怖", "Genre3": "-", "CAST1": "彭禺厶", "CAST2": "王萌", "CAST3": "周凯文", "CAST4": "曹琦", "CAST5": "孟子叶"},
{"Irank": "41", "MovieName": "夜半凶铃", "BoxOffice": "881597.0", "SumBoxOffice": "881597.0", "Director": "李耀东", "Genre1": "悬疑", "Genre2": "恐怖", "Genre3": "-", "CAST1": "刘青", "CAST2": "李浩轩", "CAST3": "白瑶", "CAST4": "贲蓝琪", "CAST5": "孙志翔"},
{"Irank": "42", "MovieName": "谁是球王", "BoxOffice": "879552.0", "SumBoxOffice": "879552.0", "Director": "裘仲维", "Genre1": "剧情", "Genre2": "喜剧", "Genre3": "-", "CAST1": "尹航", "CAST2": "代旭", "CAST3": "李晨浩", "CAST4": "衣云鹤", "CAST5": "张念骅"},
{"Irank": "44", "MovieName": "银魂", "BoxOffice": "776931.0", "SumBoxOffice": "776931.0", "Director": "福田雄一", "Genre1": "喜剧", "Genre2": "动作", "Genre3": "奇幻", "CAST1": "小栗旬", "CAST2": "菅田将晖", "CAST3": "桥本环奈", "CAST4": "柳乐优弥", "CAST5": "新井浩文"},
{"Irank": "45", "MovieName": "胖女不愁嫁", "BoxOffice": "747087.0", "SumBoxOffice": "747087.0", "Director": "杨奕黎", "Genre1": "喜剧", "Genre2": "-", "Genre3": "-", "CAST1": "巫迪文", "CAST2": "张莉莎", "CAST3": "吴云飞", "CAST4": "刘刚", "CAST5": "-"},
{"Irank": "46", "MovieName": "冈仁波齐", "BoxOffice": "724051.0", "SumBoxOffice": "724051.0", "Director": "张杨", "Genre1": "剧情", "Genre2": "-", "Genre3": "-", "CAST1": "尼玛扎堆", "CAST2": "杨培", "CAST3": "索朗卓嘎", "CAST4": "次仁曲珍", "CAST5": "色巴江措"},
{"Irank": "47", "MovieName": "绝技情缘之艺魂", "BoxOffice": "512158.0", "SumBoxOffice": "512158.0", "Director": "张建成", "Genre1": "剧情", "Genre2": "爱情", "Genre3": "-", "CAST1": "童苡萱", "CAST2": "杜奕衡", "CAST3": "曹帅", "CAST4": "杨涵斌", "CAST5": "曾杰"},
{"Irank": "48", "MovieName": "一路向爱", "BoxOffice": "510456.0", "SumBoxOffice": "510456.0", "Director": "徐艺华", "Genre1": "剧情", "Genre2": "爱情", "Genre3": "-", "CAST1": "高姝瑶", "CAST2": "范植伟", "CAST3": "-", "CAST4": "-", "CAST5": "-"},
{"Irank": "49", "MovieName": "阳光萌星社", "BoxOffice": "497225.0", "SumBoxOffice": "497225.0", "Director": "刘凌", "Genre1": "-", "Genre2": "-", "Genre3": "-", "CAST1": "金子", "CAST2": "郭小雨", "CAST3": "石晨", "CAST4": "冯思米", "CAST5": "-"},
{"Irank": "50", "MovieName": "绿野仙踪之奥兹国奇幻之旅", "BoxOffice": "375626.0", "SumBoxOffice": "375626.0", "Director": "费多·德米提亚夫", "Genre1": "动画", "Genre2": "家庭", "Genre3": "冒险", "CAST1": "Dmitriy Dyuzhev", "CAST2": "康斯坦丁·哈宾斯基", "CAST3": "谢尔盖·希纳罗维", "CAST4": "-", "CAST5": "-"},
{"Irank": "51", "MovieName": "战狼", "BoxOffice": "342540.0", "SumBoxOffice": "342540.0", "Director": "吴京", "Genre1": "动作", "Genre2": "战争", "Genre3": "-", "CAST1": "吴京", "CAST2": "余男", "CAST3": "斯科特·阿金斯", "CAST4": "凯文·李", "CAST5": "倪大红"},
{"Irank": "53", "MovieName": "摇摇晃晃的人间", "BoxOffice": "299503.0", "SumBoxOffice": "299503.0", "Director": "范俭", "Genre1": "纪录片", "Genre2": "传记", "Genre3": "-", "CAST1": "余秀华", "CAST2": "周金香", "CAST3": "余文海", "CAST4": "尹世平", "CAST5": "-"},
{"Irank": "55", "MovieName": "京城81号2", "BoxOffice": "261299.0", "SumBoxOffice": "261299.0", "Director": "钱人豪", "Genre1": "剧情", "Genre2": "悬疑", "Genre3": "惊悚", "CAST1": "张智霖", "CAST2": "梅婷", "CAST3": "钟欣潼", "CAST4": "耿乐", "CAST5": "邬君梅"},
{"Irank": "56", "MovieName": "深夜食堂2", "BoxOffice": "248321.0", "SumBoxOffice": "248321.0", "Director": "松冈锭司", "Genre1": "剧情", "Genre2": "-", "Genre3": "-", "CAST1": "小林薰", "CAST2": "河井青叶", "CAST3": "佐藤浩市", "CAST4": "池松壮亮", "CAST5": "木村绿子"},
{"Irank": "57", "MovieName": "穆桂英挂帅", "BoxOffice": "231520.0", "SumBoxOffice": "231520.0", "Director": "夏钢", "Genre1": "戏曲", "Genre2": "-", "Genre3": "-", "CAST1": "李胜素", "CAST2": "于魁智", "CAST3": "袁慧琴", "CAST4": "杨赤", "CAST5": "杜喆"},
{"Irank": "59", "MovieName": "荒野加油站", "BoxOffice": "190478.0", "SumBoxOffice": "190478.0", "Director": "赵崼", "Genre1": "悬疑", "Genre2": "恐怖", "Genre3": "-", "CAST1": "旺卓措", "CAST2": "刘承宙", "CAST3": "高欣生", "CAST4": "段楠", "CAST5": "来钰"},
{"Irank": "60", "MovieName": "喵星人", "BoxOffice": "179808.0", "SumBoxOffice": "179808.0", "Director": "陈木胜", "Genre1": "喜剧", "Genre2": "儿童", "Genre3": "奇幻", "CAST1": "古天乐", "CAST2": "马丽", "CAST3": "刘楚恬", "CAST4": "黄星羱", "CAST5": "阮兆祥"},
{"Irank": "64", "MovieName": "原罪的羔羊", "BoxOffice": "113493.0", "SumBoxOffice": "113493.0", "Director": "闫国喜", "Genre1": "悬疑", "Genre2": "-", "Genre3": "-", "CAST1": "周鹏雨", "CAST2": "穆建荣", "CAST3": "陈泽帆", "CAST4": "鹿露", "CAST5": "宋星成"},
{"Irank": "65", "MovieName": "重返·狼群", "BoxOffice": "110545.0", "SumBoxOffice": "110545.0", "Director": "亦风", "Genre1": "纪录片", "Genre2": "-", "Genre3": "-", "CAST1": "李微漪", "CAST2": "-", "CAST3": "-", "CAST4": "-", "CAST5": "-"},
{"Irank": "66", "MovieName": "神灵寨", "BoxOffice": "103935.0", "SumBoxOffice": "103935.0", "Director": "潘晓斌", "Genre1": "喜剧", "Genre2": "爱情", "Genre3": "-", "CAST1": "丹尼斯·威缇可宁", "CAST2": "黄英", "CAST3": "王永峰", "CAST4": "许之糯", "CAST5": "王家珧"},
{"Irank": "67", "MovieName": "双手洪拳", "BoxOffice": "102174.0", "SumBoxOffice": "102174.0", "Director": "胡军", "Genre1": "剧情", "Genre2": "-", "Genre3": "-", "CAST1": "狄威", "CAST2": "阎玺", "CAST3": "龚洁影", "CAST4": "任添琪", "CAST5": "冯子翰"},
{"Irank": "68", "MovieName": "真爱禁区", "BoxOffice": "96552.1", "SumBoxOffice": "96552.1", "Director": "林溪", "Genre1": "爱情", "Genre2": "-", "Genre3": "-", "CAST1": "叶鹏", "CAST2": "陈奕静", "CAST3": "陈欣孺", "CAST4": "-", "CAST5": "-"},
{"Irank": "69", "MovieName": "顺德人家之合家欢", "BoxOffice": "86490.0", "SumBoxOffice": "86490.0", "Director": "杜翛然", "Genre1": "剧情", "Genre2": "喜剧", "Genre3": "爱情", "CAST1": "宋艾橦", "CAST2": "冼兆天", "CAST3": "刘天蔚", "CAST4": "梁敏", "CAST5": "张耀天"},
{"Irank": "70", "MovieName": "和田玉传奇", "BoxOffice": "85602.0", "SumBoxOffice": "85602.0", "Director": "郭松", "Genre1": "剧情", "Genre2": "-", "Genre3": "-", "CAST1": "唐文龙", "CAST2": "王一楠", "CAST3": "任正斌", "CAST4": "傅斌", "CAST5": "傅莹莹"},
{"Irank": "71", "MovieName": "石榴花开", "BoxOffice": "85134.5", "SumBoxOffice": "85134.5", "Director": "李科", "Genre1": "剧情", "Genre2": "喜剧", "Genre3": "爱情", "CAST1": "宋铁梁", "CAST2": "袁倩", "CAST3": "徐国生", "CAST4": "吴宝珠", "CAST5": "刘长青"},
{"Irank": "72", "MovieName": "赶牲灵", "BoxOffice": "67531.0", "SumBoxOffice": "67531.0", "Director": "凌淋", "Genre1": "剧情", "Genre2": "-", "Genre3": "-", "CAST1": "延翔", "CAST2": "汪碧清", "CAST3": "厉家兵", "CAST4": "杨未希", "CAST5": "-"},
{"Irank": "74", "MovieName": "让爱活下去", "BoxOffice": "64418.6", "SumBoxOffice": "64418.6", "Director": "查文白", "Genre1": "剧情", "Genre2": "-", "Genre3": "-", "CAST1": "夏德俊", "CAST2": "郑佩佩", "CAST3": "周诗璇", "CAST4": "李夏佩", "CAST5": "李文俊"},
{"Irank": "75", "MovieName": "租婚男女", "BoxOffice": "53121.6", "SumBoxOffice": "53121.6", "Director": "屈建龙", "Genre1": "剧情", "Genre2": "喜剧", "Genre3": "爱情", "CAST1": "田家达", "CAST2": "陈美行", "CAST3": "何宗龙", "CAST4": "李嘉诺", "CAST5": "肜耀忠"},
{"Irank": "78", "MovieName": "杜丽娘", "BoxOffice": "52188.6", "SumBoxOffice": "52188.6", "Director": "阳春", "Genre1": "爱情", "Genre2": "古装", "Genre3": "-", "CAST1": "陈婧涵", "CAST2": "李云鹤", "CAST3": "李琳琳", "CAST4": "刘凡", "CAST5": "-"},
{"Irank": "80", "MovieName": "我是医生", "BoxOffice": "50475.0", "SumBoxOffice": "50475.0", "Director": "谢鸣晓", "Genre1": "剧情", "Genre2": "-", "Genre3": "-", "CAST1": "赵有亮", "CAST2": "胡亚捷", "CAST3": "赵静", "CAST4": "虞嘉娜", "CAST5": "-"},
{"Irank": "81", "MovieName": "摔跤吧！爸爸", "BoxOffice": "50000.0", "SumBoxOffice": "50000.0", "Director": "涅提·蒂瓦里", "Genre1": "剧情", "Genre2": "家庭", "Genre3": "传记", "CAST1": "阿米尔·汗", "CAST2": "法缇玛·萨那·纱卡", "CAST3": "桑亚·玛荷塔", "CAST4": "阿帕尔夏克提·库拉那", "CAST5": "沙克希·坦沃"},
{"Irank": "82", "MovieName": "内心引力", "BoxOffice": "44783.0", "SumBoxOffice": "44783.0", "Director": "施秋荣", "Genre1": "纪录片", "Genre2": "-", "Genre3": "-", "CAST1": "把文翰", "CAST2": "钱小华", "CAST3": "庄崧冽", "CAST4": "吴永红", "CAST5": "钱海英"},
{"Irank": "83", "MovieName": "诗魂风流", "BoxOffice": "43097.0", "SumBoxOffice": "43097.0", "Director": "夏运华", "Genre1": "戏曲", "Genre2": "-", "Genre3": "-", "CAST1": "史依弘", "CAST2": "凌珂", "CAST3": "-", "CAST4": "-", "CAST5": "-"},
{"Irank": "84", "MovieName": "麦豆的夏天", "BoxOffice": "42733.0", "SumBoxOffice": "42733.0", "Director": "马和平", "Genre1": "儿童", "Genre2": "-", "Genre3": "-", "CAST1": "刘宗健", "CAST2": "王思宁", "CAST3": "赵纪东", "CAST4": "田广硕", "CAST5": "樊明硕"},
{"Irank": "85", "MovieName": "青海湖畔", "BoxOffice": "42711.0", "SumBoxOffice": "42711.0", "Director": "沈星浩", "Genre1": "剧情", "Genre2": "-", "Genre3": "-", "CAST1": "秦怡", "CAST2": "江平", "CAST3": "舒畅", "CAST4": "黄宏", "CAST5": "佟瑞欣"},
{"Irank": "87", "MovieName": "魔镜奇缘", "BoxOffice": "40308.0", "SumBoxOffice": "40308.0", "Director": "郑成峰", "Genre1": "动画", "Genre2": "家庭", "Genre3": "奇幻", "CAST1": "琪琪", "CAST2": "王琪", "CAST3": "孙科", "CAST4": "叶方", "CAST5": "仰洋"},
{"Irank": "91", "MovieName": "战刀屠狼", "BoxOffice": "35897.0", "SumBoxOffice": "35897.0", "Director": "刘艳杰", "Genre1": "剧情", "Genre2": "犯罪", "Genre3": "-", "CAST1": "张永达", "CAST2": "庄小龙", "CAST3": "李相炫", "CAST4": "张凯", "CAST5": "龙馨悦"},
{"Irank": "93", "MovieName": "湄公河行动", "BoxOffice": "35285.0", "SumBoxOffice": "35285.0", "Director": "林超贤", "Genre1": "动作", "Genre2": "犯罪", "Genre3": "-", "CAST1": "张涵予", "CAST2": "彭于晏", "CAST3": "孙淳", "CAST4": "陈宝国", "CAST5": "冯文娟"},
{"Irank": "94", "MovieName": "异形：契约", "BoxOffice": "33742.9", "SumBoxOffice": "33742.9", "Director": "雷德利·斯科特", "Genre1": "科幻", "Genre2": "恐怖", "Genre3": "-", "CAST1": "迈克尔·法斯宾德", "CAST2": "凯瑟琳·沃特斯顿", "CAST3": "比利·克鲁德普", "CAST4": "丹尼·麦克布莱德", "CAST5": "德米安·比齐尔"},
{"Irank": "95", "MovieName": "谢瑶环", "BoxOffice": "30200.0", "SumBoxOffice": "30200.0", "Director": "马崇杰", "Genre1": "戏曲", "Genre2": "-", "Genre3": "-", "CAST1": "丁晓君", "CAST2": "金喜全", "CAST3": "王艳", "CAST4": "窦晓璇", "CAST5": "-"},
{"Irank": "96", "MovieName": "浪花岛之恋", "BoxOffice": "29551.0", "SumBoxOffice": "29551.0", "Director": "叶哲欣", "Genre1": "剧情", "Genre2": "爱情", "Genre3": "-", "CAST1": "邓明将", "CAST2": "王雷方", "CAST3": "塔娜花日", "CAST4": "孔轩", "CAST5": "-"},
{"Irank": "97", "MovieName": "谜域之噬魂岭", "BoxOffice": "28094.5", "SumBoxOffice": "28094.5", "Director": "戴维", "Genre1": "悬疑", "Genre2": "惊悚", "Genre3": "恐怖", "CAST1": "李果", "CAST2": "闫鹿杨", "CAST3": "庄森", "CAST4": "谢钟灵", "CAST5": "朱洪振"},
{"Irank": "98", "MovieName": "狼图腾", "BoxOffice": "27934.0", "SumBoxOffice": "27934.0", "Director": "让-雅克·阿诺", "Genre1": "剧情", "Genre2": "冒险", "Genre3": "-", "CAST1": "冯绍峰", "CAST2": "窦骁", "CAST3": "昂哈妮玛", "CAST4": "巴森", "CAST5": "尹铸胜"},
{"Irank": "99", "MovieName": "阿里巴巴大盗奇兵", "BoxOffice": "27364.5", "SumBoxOffice": "27364.5", "Director": "郑成峰", "Genre1": "喜剧", "Genre2": "动画", "Genre3": "冒险", "CAST1": "叶芳", "CAST2": "丁妍", "CAST3": "张洋", "CAST4": "吴瑞", "CAST5": "仰洋"},
{"Irank": "100", "MovieName": "闯堂兔2疯狂马戏团", "BoxOffice": "26909.6", "SumBoxOffice": "26909.6", "Director": "曾宪林", "Genre1": "喜剧", "Genre2": "动画", "Genre3": "儿童", "CAST1": "小连杀", "CAST2": "叮当", "CAST3": "郝祥海", "CAST4": "王幸", "CAST5": "王祺"},
{"Irank": "103", "MovieName": "绝世高手", "BoxOffice": "22757.0", "SumBoxOffice": "22757.0", "Director": "卢正雨", "Genre1": "喜剧", "Genre2": "动作", "Genre3": "-", "CAST1": "卢正雨", "CAST2": "郭采洁", "CAST3": "范伟", "CAST4": "蔡国庆", "CAST5": "陈冲"},
{"Irank": "105", "MovieName": "茶盗", "BoxOffice": "20213.0", "SumBoxOffice": "20213.0", "Director": "潘富荣", "Genre1": "剧情", "Genre2": "动作", "Genre3": "-", "CAST1": "梁小龙", "CAST2": "姜明月", "CAST3": "陈市", "CAST4": "李咚咚", "CAST5": "吴文"},
{"Irank": "106", "MovieName": "红线2017", "BoxOffice": "20150.0", "SumBoxOffice": "20150.0", "Director": "王野", "Genre1": "剧情", "Genre2": "悬疑", "Genre3": "犯罪", "CAST1": "郝平", "CAST2": "张潮", "CAST3": "陈奕鸣", "CAST4": "王一峰", "CAST5": "李思睿"},
{"Irank": "108", "MovieName": "八月", "BoxOffice": "15435.2", "SumBoxOffice": "15435.2", "Director": "张大磊", "Genre1": "剧情", "Genre2": "-", "Genre3": "-", "CAST1": "孔维一", "CAST2": "张晨", "CAST3": "郭燕芸", "CAST4": "-", "CAST5": "-"},
{"Irank": "110", "MovieName": "特功明星", "BoxOffice": "14000.0", "SumBoxOffice": "14000.0", "Director": "徐克", "Genre1": "喜剧", "Genre2": "动作", "Genre3": "动画", "CAST1": "黄莺", "CAST2": "曹真", "CAST3": "张安琪", "CAST4": "李正翔", "CAST5": "程玉珠"},
{"Irank": "112", "MovieName": "青禾男高", "BoxOffice": "12993.0", "SumBoxOffice": "12993.0", "Director": "蒋卓原", "Genre1": "剧情", "Genre2": "-", "Genre3": "-", "CAST1": "景甜", "CAST2": "欧豪", "CAST3": "黑木美沙", "CAST4": "林遣都", "CAST5": "张宁江"},
{"Irank": "114", "MovieName": "七天", "BoxOffice": "10421.0", "SumBoxOffice": "10421.0", "Director": "李连军", "Genre1": "爱情", "Genre2": "悬疑", "Genre3": "犯罪", "CAST1": "李涛亮", "CAST2": "刘真君", "CAST3": "-", "CAST4": "-", "CAST5": "-"},
{"Irank": "118", "MovieName": "S的秘密", "BoxOffice": "8528.0", "SumBoxOffice": "8528.0", "Director": "徐林", "Genre1": "剧情", "Genre2": "爱情", "Genre3": "-", "CAST1": "吴启华", "CAST2": "麦家琪", "CAST3": "章小军", "CAST4": "房星彤", "CAST5": "杨能"},
{"Irank": "119", "MovieName": "明月几时有", "BoxOffice": "8110.0", "SumBoxOffice": "8110.0", "Director": "许鞍华", "Genre1": "剧情", "Genre2": "历史", "Genre3": "战争", "CAST1": "周迅", "CAST2": "彭于晏", "CAST3": "霍建华", "CAST4": "叶德娴", "CAST5": "郭涛"},
{"Irank": "120", "MovieName": "我的诗篇", "BoxOffice": "8099.0", "SumBoxOffice": "8099.0", "Director": "吴飞跃", "Genre1": "纪录片", "Genre2": "-", "Genre3": "-", "CAST1": "陈年喜", "CAST2": "邬霞", "CAST3": "乌鸟鸟", "CAST4": "老井", "CAST5": "吉克阿优"},
{"Irank": "121", "MovieName": "桃花梦", "BoxOffice": "7698.0", "SumBoxOffice": "7698.0", "Director": "朱江华", "Genre1": "剧情", "Genre2": "-", "Genre3": "-", "CAST1": "王靖云", "CAST2": "孙渤洋", "CAST3": "甘伟雄", "CAST4": "陈锦瑶", "CAST5": "-"},
{"Irank": "123", "MovieName": "我在故宫修文物", "BoxOffice": "6782.0", "SumBoxOffice": "6782.0", "Director": "萧寒", "Genre1": "纪录片", "Genre2": "-", "Genre3": "-", "CAST1": "王津", "CAST2": "亓昊楠", "CAST3": "屈峰", "CAST4": "王五胜", "CAST5": "王有亮"},
{"Irank": "124", "MovieName": "领袖1935", "BoxOffice": "6715.0", "SumBoxOffice": "6715.0", "Director": "周琦", "Genre1": "剧情", "Genre2": "-", "Genre3": "-", "CAST1": "王晖", "CAST2": "刘劲", "CAST3": "吴京安", "CAST4": "王伍福", "CAST5": "脱一然"},
{"Irank": "125", "MovieName": "铁道飞虎", "BoxOffice": "6484.0", "SumBoxOffice": "6484.0", "Director": "丁晟", "Genre1": "喜剧", "Genre2": "动作", "Genre3": "-", "CAST1": "成龙", "CAST2": "黄子韬", "CAST3": "王凯", "CAST4": "王大陆", "CAST5": "徐帆"},
{"Irank": "127", "MovieName": "大脚印", "BoxOffice": "5408.0", "SumBoxOffice": "5408.0", "Director": "伊桑・韦利", "Genre1": "动作", "Genre2": "家庭", "Genre3": "冒险", "CAST1": "萨沙·杰克逊", "CAST2": "曹操", "CAST3": "道格拉斯·泰特", "CAST4": "-", "CAST5": "-"},
{"Irank": "129", "MovieName": "与君相恋100次", "BoxOffice": "4893.25", "SumBoxOffice": "4893.25", "Director": "月川翔", "Genre1": "爱情", "Genre2": "-", "Genre3": "-", "CAST1": "miwa", "CAST2": "坂口健太郎", "CAST3": "龙星凉", "CAST4": "真野惠里菜", "CAST5": "泉泽祐希"},
{"Irank": "132", "MovieName": "一家两口", "BoxOffice": "4633.0", "SumBoxOffice": "4633.0", "Director": "张亚男", "Genre1": "剧情", "Genre2": "喜剧", "Genre3": "-", "CAST1": "马仑", "CAST2": "李勤勤", "CAST3": "方青卓", "CAST4": "-", "CAST5": "-"},
{"Irank": "133", "MovieName": "冬", "BoxOffice": "4255.0", "SumBoxOffice": "4255.0", "Director": "邢健", "Genre1": "剧情", "Genre2": "-", "Genre3": "-", "CAST1": "王德顺", "CAST2": "王诗雯淇", "CAST3": "黄嵩博", "CAST4": "徐文宇", "CAST5": "朴政希"},
{"Irank": "134", "MovieName": "青春逗", "BoxOffice": "4226.0", "SumBoxOffice": "4226.0", "Director": "郑仕明", "Genre1": "剧情", "Genre2": "喜剧", "Genre3": "-", "CAST1": "姜潮", "CAST2": "张嘉倪", "CAST3": "金恩圣", "CAST4": "于文文", "CAST5": "马春瑞"},
{"Irank": "136", "MovieName": "杀破狼2", "BoxOffice": "4047.6", "SumBoxOffice": "4047.6", "Director": "郑保瑞", "Genre1": "剧情", "Genre2": "动作", "Genre3": "犯罪", "CAST1": "吴京", "CAST2": "托尼·贾", "CAST3": "张晋", "CAST4": "任达华", "CAST5": "卢惠光"},
{"Irank": "138", "MovieName": "赛尔号5：雷神崛起", "BoxOffice": "3430.0", "SumBoxOffice": "3430.0", "Director": "王章俊", "Genre1": "剧情", "Genre2": "动画", "Genre3": "儿童", "CAST1": "罗玉婷", "CAST2": "翟巍", "CAST3": "王晓彤", "CAST4": "孙晔", "CAST5": "吴磊"},
{"Irank": "140", "MovieName": "生门", "BoxOffice": "3298.0", "SumBoxOffice": "3298.0", "Director": "陈为军", "Genre1": "纪录片", "Genre2": "-", "Genre3": "-", "CAST1": "李家福", "CAST2": "夏锦菊", "CAST3": "陈小凤", "CAST4": "曾宪春", "CAST5": "-"},
{"Irank": "143", "MovieName": "黑猫警长之翡翠之星", "BoxOffice": "2727.93", "SumBoxOffice": "2727.93", "Director": "于胜军", "Genre1": "喜剧", "Genre2": "动作", "Genre3": "科幻", "CAST1": "赵路", "CAST2": "吴天昊", "CAST3": "林子杰", "CAST4": "刘莹", "CAST5": "程玉珠"},
{"Irank": "144", "MovieName": "贫穷富爸爸", "BoxOffice": "2450.0", "SumBoxOffice": "2450.0", "Director": "张坚庭", "Genre1": "剧情", "Genre2": "喜剧", "Genre3": "爱情", "CAST1": "郑嘉颖", "CAST2": "小小彬", "CAST3": "李呈媛", "CAST4": "刘心悠", "CAST5": "-"},
{"Irank": "145", "MovieName": "红军小学", "BoxOffice": "2440.0", "SumBoxOffice": "2440.0", "Director": "丁林", "Genre1": "剧情", "Genre2": "历史", "Genre3": "-", "CAST1": "谯丹", "CAST2": "唐楚梵", "CAST3": "侯定江", "CAST4": "廖震", "CAST5": "张祎格"},
{"Irank": "146", "MovieName": "喜羊羊与灰太狼之羊年喜羊羊", "BoxOffice": "2400.0", "SumBoxOffice": "2400.0", "Director": "黄伟明", "Genre1": "喜剧", "Genre2": "动画", "Genre3": "家庭", "CAST1": "祖晴", "CAST2": "张琳", "CAST3": "杨阳洋", "CAST4": "高全胜", "CAST5": "梁颖"},
{"Irank": "147", "MovieName": "伊犁河谷", "BoxOffice": "2360.0", "SumBoxOffice": "2360.0", "Director": "金韬", "Genre1": "剧情", "Genre2": "爱情", "Genre3": "-", "CAST1": "宋佳伦", "CAST2": "傅天骄", "CAST3": "冯文娟", "CAST4": "李泓良", "CAST5": "-"},
{"Irank": "149", "MovieName": "艺术也疯狂", "BoxOffice": "2290.0", "SumBoxOffice": "2290.0", "Director": "蔡玉水", "Genre1": "剧情", "Genre2": "喜剧", "Genre3": "-", "CAST1": "张岩", "CAST2": "王德顺", "CAST3": "蔡宜恒", "CAST4": "英壮", "CAST5": "杜旭东"},
{"Irank": "152", "MovieName": "牡丹仙子之皇帝诏曰", "BoxOffice": "2000.0", "SumBoxOffice": "2000.0", "Director": "彭军", "Genre1": "爱情", "Genre2": "奇幻", "Genre3": "-", "CAST1": "袁菲", "CAST2": "黄榛", "CAST3": "郭丰周", "CAST4": "陈烨", "CAST5": "刘卫华"},
{"Irank": "153", "MovieName": "以爱为名", "BoxOffice": "2000.0", "SumBoxOffice": "2000.0", "Director": "王毓雅", "Genre1": "剧情", "Genre2": "喜剧", "Genre3": "-", "CAST1": "王奕瑾", "CAST2": "黄恺杰", "CAST3": "卞庆华", "CAST4": "钱柏渝", "CAST5": "蔡尚甫"},
{"Irank": "154", "MovieName": "情圣", "BoxOffice": "1839.9", "SumBoxOffice": "1839.9", "Director": "宋晓飞", "Genre1": "喜剧", "Genre2": "-", "Genre3": "-", "CAST1": "肖央", "CAST2": "闫妮", "CAST3": "小沈阳", "CAST4": "乔杉", "CAST5": "艾伦"},
{"Irank": "155", "MovieName": "泰迪熊之玩具大战", "BoxOffice": "1800.0", "SumBoxOffice": "1800.0", "Director": "胡韵", "Genre1": "喜剧", "Genre2": "动画", "Genre3": "-", "CAST1": "邓小婷", "CAST2": "赵奔", "CAST3": "白文显", "CAST4": "孙亚军", "CAST5": "-"},
{"Irank": "158", "MovieName": "苏州少年横漂记", "BoxOffice": "1510.0", "SumBoxOffice": "1510.0", "Director": "陈剑", "Genre1": "动作", "Genre2": "-", "Genre3": "-", "CAST1": "黄梓乘", "CAST2": "石天龙", "CAST3": "黄海冰", "CAST4": "袁苑", "CAST5": "孟潞"},
{"Irank": "159", "MovieName": "猪猪侠之英雄猪少年", "BoxOffice": "1480.0", "SumBoxOffice": "1480.0", "Director": "陆锦明", "Genre1": "喜剧", "Genre2": "动画", "Genre3": "奇幻", "CAST1": "易烊千玺", "CAST2": "陈轶", "CAST3": "张子琨", "CAST4": "戎妍", "CAST5": "庄承松"},
{"Irank": "162", "MovieName": "原谅他77次", "BoxOffice": "1275.0", "SumBoxOffice": "1275.0", "Director": "邱礼涛", "Genre1": "爱情", "Genre2": "-", "Genre3": "-", "CAST1": "蔡卓妍", "CAST2": "周柏豪", "CAST3": "卫诗雅", "CAST4": "钟欣潼", "CAST5": "卢巧音"},
{"Irank": "164", "MovieName": "牧野传奇", "BoxOffice": "1240.0", "SumBoxOffice": "1240.0", "Director": "谢宝锐", "Genre1": "动画", "Genre2": "-", "Genre3": "-", "CAST1": "-", "CAST2": "-", "CAST3": "-", "CAST4": "-", "CAST5": "-"},
{"Irank": "165", "MovieName": "圣诞大赢家", "BoxOffice": "1230.0", "SumBoxOffice": "1230.0", "Director": "毛呆", "Genre1": "喜剧", "Genre2": "动画", "Genre3": "-", "CAST1": "宝木中阳", "CAST2": "阿杰", "CAST3": "小连杀", "CAST4": "叮当", "CAST5": "藤新"},
{"Irank": "166", "MovieName": "反转人生", "BoxOffice": "1200.0", "SumBoxOffice": "1200.0", "Director": "伍仕贤", "Genre1": "喜剧", "Genre2": "奇幻", "Genre3": "-", "CAST1": "夏雨", "CAST2": "闫妮", "CAST3": "潘斌龙", "CAST4": "宋茜", "CAST5": "吴大维"},
{"Irank": "170", "MovieName": "爱爱囧事2", "BoxOffice": "1148.0", "SumBoxOffice": "1148.0", "Director": "关尔", "Genre1": "剧情", "Genre2": "喜剧", "Genre3": "爱情", "CAST1": "向昊", "CAST2": "李小晶", "CAST3": "赵吉", "CAST4": "李思雯", "CAST5": "陈宇星"},
{"Irank": "173", "MovieName": "喜欢你", "BoxOffice": "1002.0", "SumBoxOffice": "1002.0", "Director": "许宏宇", "Genre1": "喜剧", "Genre2": "爱情", "Genre3": "-", "CAST1": "金城武", "CAST2": "周冬雨", "CAST3": "孙艺洲", "CAST4": "奚梦瑶", "CAST5": "杨祐宁"},
{"Irank": "174", "MovieName": "爱上试睡师", "BoxOffice": "1000.0", "SumBoxOffice": "1000.0", "Director": "罗登", "Genre1": "喜剧", "Genre2": "爱情", "Genre3": "-", "CAST1": "丹尼斯·吴", "CAST2": "唐婧", "CAST3": "肖旭", "CAST4": "刘栋", "CAST5": "-"},
{"Irank": "175", "MovieName": "整形师·脸", "BoxOffice": "1000.0", "SumBoxOffice": "1000.0", "Director": "黄军", "Genre1": "悬疑", "Genre2": "惊悚", "Genre3": "-", "CAST1": "浦蒲", "CAST2": "李雯雯", "CAST3": "方慧", "CAST4": "孙祖君", "CAST5": "刘天佐"},
{"Irank": "176", "MovieName": "提着心吊着胆", "BoxOffice": "1000.0", "SumBoxOffice": "1000.0", "Director": "李雨禾", "Genre1": "剧情", "Genre2": "喜剧", "Genre3": "悬疑", "CAST1": "陈玺旭", "CAST2": "高叶", "CAST3": "任素汐", "CAST4": "董博", "CAST5": "楼云飞"},
{"Irank": "177", "MovieName": "爸爸的3次婚礼", "BoxOffice": "1000.0", "SumBoxOffice": "1000.0", "Director": "马楚成", "Genre1": "喜剧", "Genre2": "爱情", "Genre3": "家庭", "CAST1": "董洁", "CAST2": "张亮", "CAST3": "孙茜", "CAST4": "隋凯", "CAST5": "张悦轩"},
{"Irank": "178", "MovieName": "浪漫搭档", "BoxOffice": "1000.0", "SumBoxOffice": "1000.0", "Director": "刘夏同", "Genre1": "喜剧", "Genre2": "动作", "Genre3": "爱情", "CAST1": "陈国坤", "CAST2": "徐冬梅", "CAST3": "刘承俊", "CAST4": "侯桐江", "CAST5": "王海祥"},
{"Irank": "179", "MovieName": "兄弟之北漂歌手", "BoxOffice": "1000.0", "SumBoxOffice": "1000.0", "Director": "王子", "Genre1": "剧情", "Genre2": "动作", "Genre3": "爱情", "CAST1": "石昊正", "CAST2": "刘佳兰", "CAST3": "廖望", "CAST4": "张艺荠", "CAST5": "庞瀚辰"},
{"Irank": "185", "MovieName": "逆时营救", "BoxOffice": "800.0", "SumBoxOffice": "800.0", "Director": "尹鸿承", "Genre1": "动作", "Genre2": "科幻", "Genre3": "-", "CAST1": "杨幂", "CAST2": "霍建华", "CAST3": "金士杰", "CAST4": "刘畅", "CAST5": "张艺瀚"},
{"Irank": "187", "MovieName": "秘果", "BoxOffice": "768.0", "SumBoxOffice": "768.0", "Director": "连奕琦", "Genre1": "爱情", "Genre2": "-", "Genre3": "-", "CAST1": "陈飞宇", "CAST2": "欧阳娜娜", "CAST3": "邹元清", "CAST4": "张诚航", "CAST5": "欧豪"},
{"Irank": "188", "MovieName": "阿里巴巴2所罗门封印", "BoxOffice": "765.0", "SumBoxOffice": "765.0", "Director": "郑成峰", "Genre1": "喜剧", "Genre2": "动画", "Genre3": "冒险", "CAST1": "丁妍", "CAST2": "叶方", "CAST3": "杨进", "CAST4": "孙科", "CAST5": "张洋"},
{"Irank": "189", "MovieName": "烈日灼心", "BoxOffice": "756.0", "SumBoxOffice": "756.0", "Director": "曹保平", "Genre1": "剧情", "Genre2": "悬疑", "Genre3": "犯罪", "CAST1": "邓超", "CAST2": "段奕宏", "CAST3": "郭涛", "CAST4": "王珞丹", "CAST5": "吕颂贤"},
{"Irank": "190", "MovieName": "最美的时候遇见你", "BoxOffice": "727.0", "SumBoxOffice": "727.0", "Director": "吴娜", "Genre1": "爱情", "Genre2": "-", "Genre3": "-", "CAST1": "谭松韵", "CAST2": "罗云熙", "CAST3": "-", "CAST4": "-", "CAST5": "-"},
{"Irank": "196", "MovieName": "港囧", "BoxOffice": "498.0", "SumBoxOffice": "498.0", "Director": "徐峥", "Genre1": "喜剧", "Genre2": "-", "Genre3": "-", "CAST1": "徐峥", "CAST2": "赵薇", "CAST3": "包贝尔", "CAST4": "杜鹃", "CAST5": "葛民辉"},
{"Irank": "199", "MovieName": "我的舞林江湖", "BoxOffice": "450.0", "SumBoxOffice": "450.0", "Director": "高跃铭", "Genre1": "剧情", "Genre2": "喜剧", "Genre3": "爱情", "CAST1": "陈承", "CAST2": "郑智勋", "CAST3": "叶禹彤", "CAST4": "王雅静", "CAST5": "李为民"},
{"Irank": "200", "MovieName": "使徒行者", "BoxOffice": "444.0", "SumBoxOffice": "444.0", "Director": "文伟鸿", "Genre1": "剧情", "Genre2": "动作", "Genre3": "犯罪", "CAST1": "张家辉", "CAST2": "古天乐", "CAST3": "吴镇宇", "CAST4": "佘诗曼", "CAST5": "许绍雄"},
{"Irank": "202", "MovieName": "疯狂动物城", "BoxOffice": "400.0", "SumBoxOffice": "400.0", "Director": "拜伦·霍华德", "Genre1": "喜剧", "Genre2": "动画", "Genre3": "冒险", "CAST1": "金妮弗·古德温", "CAST2": "杰森·贝特曼", "CAST3": "伊德里斯·艾尔巴", "CAST4": "珍妮·斯蕾特", "CAST5": "内特·托伦斯"},
{"Irank": "206", "MovieName": "草原英雄小姐妹", "BoxOffice": "344.0", "SumBoxOffice": "344.0", "Director": "包·那音太", "Genre1": "剧情", "Genre2": "-", "Genre3": "-", "CAST1": "包海龙", "CAST2": "忽蓝", "CAST3": "苏雅拉其其格", "CAST4": "娜木罕", "CAST5": "-"},
{"Irank": "207", "MovieName": "夏洛特烦恼", "BoxOffice": "330.0", "SumBoxOffice": "330.0", "Director": "闫非", "Genre1": "喜剧", "Genre2": "爱情", "Genre3": "-", "CAST1": "沈腾", "CAST2": "马丽", "CAST3": "尹正", "CAST4": "艾伦", "CAST5": "王智"},
{"Irank": "210", "MovieName": "霸王别姬（京剧）", "BoxOffice": "291.0", "SumBoxOffice": "291.0", "Director": "滕俊杰", "Genre1": "戏曲", "Genre2": "-", "Genre3": "-", "CAST1": "尚长荣", "CAST2": "史依弘", "CAST3": "杨东虎", "CAST4": "蓝天", "CAST5": "李军"},
{"Irank": "211", "MovieName": "微微一笑很倾城", "BoxOffice": "286.85", "SumBoxOffice": "286.85", "Director": "赵天宇", "Genre1": "爱情", "Genre2": "-", "Genre3": "-", "CAST1": "井柏然", "CAST2": "杨颖", "CAST3": "李沁", "CAST4": "王思聪", "CAST5": "刘循子墨"},
{"Irank": "214", "MovieName": "片甲不留", "BoxOffice": "220.0", "SumBoxOffice": "220.0", "Director": "李抒航", "Genre1": "剧情", "Genre2": "动作", "Genre3": "传记", "CAST1": "李抒航", "CAST2": "张定涵", "CAST3": "徐少强", "CAST4": "贺生伟", "CAST5": "何昊阳"},
{"Irank": "215", "MovieName": "蜜月计划", "BoxOffice": "220.0", "SumBoxOffice": "220.0", "Director": "颢然", "Genre1": "喜剧", "Genre2": "爱情", "Genre3": "-", "CAST1": "孙坚", "CAST2": "陈燃", "CAST3": "汪洋", "CAST4": "王学敏", "CAST5": "齐超"},
{"Irank": "217", "MovieName": "我们诞生在中国", "BoxOffice": "194.0", "SumBoxOffice": "194.0", "Director": "陆川", "Genre1": "剧情", "Genre2": "纪录片", "Genre3": "-", "CAST1": "周迅", "CAST2": "约翰·卡拉辛斯基", "CAST3": "-", "CAST4": "-", "CAST5": "-"},
{"Irank": "218", "MovieName": "唐人街探案", "BoxOffice": "190.0", "SumBoxOffice": "190.0", "Director": "陈思诚", "Genre1": "喜剧", "Genre2": "动作", "Genre3": "悬疑", "CAST1": "王宝强", "CAST2": "刘昊然", "CAST3": "佟丽娅", "CAST4": "陈赫", "CAST5": "肖央"},
{"Irank": "219", "MovieName": "果宝特攻之水果大逃亡", "BoxOffice": "179.0", "SumBoxOffice": "179.0", "Director": "王巍", "Genre1": "喜剧", "Genre2": "动画", "Genre3": "冒险", "CAST1": "赖虹宇", "CAST2": "祖晴", "CAST3": "鞠月斌", "CAST4": "申克", "CAST5": "王巍"},
{"Irank": "225", "MovieName": "萧何月下追韩信（京剧）", "BoxOffice": "96.0", "SumBoxOffice": "96.0", "Director": "朱伟刚", "Genre1": "戏曲", "Genre2": "-", "Genre3": "-", "CAST1": "陈少云", "CAST2": "傅希如", "CAST3": "何澍", "CAST4": "严庆谷", "CAST5": "金喜全"},
{"Irank": "228", "MovieName": "爸爸的假期", "BoxOffice": "68.2", "SumBoxOffice": "68.2", "Director": "王岳伦", "Genre1": "喜剧", "Genre2": "家庭", "Genre3": "-", "CAST1": "郭涛", "CAST2": "林志颖", "CAST3": "张亮", "CAST4": "王岳伦", "CAST5": "田亮"},
{"Irank": "233", "MovieName": "我们停战吧", "BoxOffice": "60.0", "SumBoxOffice": "60.0", "Director": "陆天华", "Genre1": "剧情", "Genre2": "爱情", "Genre3": "-", "CAST1": "林文龙", "CAST2": "林熹瞳", "CAST3": "谭耀文", "CAST4": "汤怡", "CAST5": "张文慈"},
{"Irank": "236", "MovieName": "诡异酒楼", "BoxOffice": "52.0", "SumBoxOffice": "52.0", "Director": "蒋国权", "Genre1": "惊悚", "Genre2": "-", "Genre3": "-", "CAST1": "欧阳鑫紫", "CAST2": "赵东昊", "CAST3": "李璐兵", "CAST4": "刘勇", "CAST5": "黎明"},
{"Irank": "239", "MovieName": "爸爸去哪儿2", "BoxOffice": "50.0", "SumBoxOffice": "50.0", "Director": "谢涤葵", "Genre1": "喜剧", "Genre2": "家庭", "Genre3": "儿童", "CAST1": "黄磊", "CAST2": "黄忆慈", "CAST3": "陆毅", "CAST4": "陆雨萱", "CAST5": "曹格"},
{"Irank": "244", "MovieName": "煎饼侠", "BoxOffice": "41.8", "SumBoxOffice": "41.8", "Director": "大鹏", "Genre1": "喜剧", "Genre2": "-", "Genre3": "-", "CAST1": "大鹏", "CAST2": "袁姗姗", "CAST3": "柳岩", "CAST4": "吴君如", "CAST5": "曾志伟"},
{"Irank": "245", "MovieName": "北纬30度之爱", "BoxOffice": "40.0", "SumBoxOffice": "40.0", "Director": "华原", "Genre1": "剧情", "Genre2": "爱情", "Genre3": "悬疑", "CAST1": "陈思娜", "CAST2": "肖宏", "CAST3": "毛渤陇", "CAST4": "兰卡初", "CAST5": "陈思妍"},
{"Irank": "248", "MovieName": "黑暗迷宫", "BoxOffice": "30.0", "SumBoxOffice": "30.0", "Director": "温河", "Genre1": "悬疑", "Genre2": "犯罪", "Genre3": "-", "CAST1": "聂远", "CAST2": "葛天", "CAST3": "杜奕衡", "CAST4": "初俊辰", "CAST5": "栾元晖"},
{"Irank": "250", "MovieName": "澳门风云2", "BoxOffice": "24.49", "SumBoxOffice": "24.49", "Director": "王晶", "Genre1": "喜剧", "Genre2": "动作", "Genre3": "-", "CAST1": "周润发", "CAST2": "张家辉", "CAST3": "刘嘉玲", "CAST4": "余文乐", "CAST5": "王诗龄"},
{"Irank": "253", "MovieName": "海鹰战警", "BoxOffice": "23.0", "SumBoxOffice": "23.0", "Director": "钟光琳", "Genre1": "剧情", "Genre2": "-", "Genre3": "-", "CAST1": "牟凤彬", "CAST2": "吴青芸", "CAST3": "张宁益", "CAST4": "王玉璋", "CAST5": "谈天"},
{"Irank": "254", "MovieName": "龙骑侠", "BoxOffice": "18.04", "SumBoxOffice": "18.04", "Director": "刘可欣", "Genre1": "动画", "Genre2": "奇幻", "Genre3": "冒险", "CAST1": "唐小喜", "CAST2": "张雪凌", "CAST3": "路知行", "CAST4": "张璐", "CAST5": "李立宏"},
{"Irank": "255", "MovieName": "快手枪手快枪手", "BoxOffice": "15.0", "SumBoxOffice": "15.0", "Director": "潘安子", "Genre1": "喜剧", "Genre2": "动作", "Genre3": "-", "CAST1": "林更新", "CAST2": "张静初", "CAST3": "腾格尔", "CAST4": "刘晓庆", "CAST5": "锦荣"},
{"Irank": "257", "MovieName": "西游记之大圣归来", "BoxOffice": "3.0", "SumBoxOffice": "3.0", "Director": "田晓鹏", "Genre1": "喜剧", "Genre2": "动作", "Genre3": "动画", "CAST1": "张磊", "CAST2": "林子杰", "CAST3": "吴文伦", "CAST4": "童自荣", "CAST5": "刘九容"},
{"Irank": "263", "MovieName": "愤怒的小鸟", "BoxOffice": "0.0", "SumBoxOffice": "0.0", "Director": "费格尔·雷利", "Genre1": "喜剧", "Genre2": "动画", "Genre3": "冒险", "CAST1": "杰森·苏戴奇斯", "CAST2": "乔什·加德", "CAST3": "丹尼·麦克布莱德", "CAST4": "玛娅·鲁道夫", "CAST5": "西恩·潘"},
{"Irank": "264", "MovieName": "寒战2", "BoxOffice": "0.0", "SumBoxOffice": "0.0", "Director": "梁乐民", "Genre1": "剧情", "Genre2": "动作", "Genre3": "犯罪", "CAST1": "郭富城", "CAST2": "梁家辉", "CAST3": "杨采妮", "CAST4": "彭于晏", "CAST5": "李治廷"},
{"Irank": "267", "MovieName": "功夫瑜伽", "BoxOffice": "0.0", "SumBoxOffice": "0.0", "Director": "唐季礼", "Genre1": "喜剧", "Genre2": "动作", "Genre3": "冒险", "CAST1": "成龙", "CAST2": "李治廷", "CAST3": "张艺兴", "CAST4": "索努·苏德", "CAST5": "母其弥雅"},
{"Irank": "268", "MovieName": "蜘蛛侠：英雄归来", "BoxOffice": "0.0", "SumBoxOffice": "0.0", "Director": "乔·沃茨", "Genre1": "动作", "Genre2": "科幻", "Genre3": "冒险", "CAST1": "汤姆·赫兰德", "CAST2": "小罗伯特·唐尼", "CAST3": "玛丽莎·托梅", "CAST4": "迈克尔·基顿", "CAST5": "雅各布·巴特朗"},
{"Irank": "269", "MovieName": "追·踪", "BoxOffice": "0.0", "SumBoxOffice": "0.0", "Director": "李霄峰", "Genre1": "剧情", "Genre2": "犯罪", "Genre3": "-", "CAST1": "罗晋", "CAST2": "聂远", "CAST3": "黄觉", "CAST4": "姜珮瑶", "CAST5": "辛鹏"},
{"Irank": "270", "MovieName": "海洋奇缘", "BoxOffice": "0.0", "SumBoxOffice": "0.0", "Director": "罗恩·克莱蒙兹", "Genre1": "动画", "Genre2": "歌舞", "Genre3": "奇幻", "CAST1": "奥丽伊·卡瓦洛", "CAST2": "道恩·强森", "CAST3": "瑞切尔·豪斯", "CAST4": "特穆拉·莫里森", "CAST5": "杰梅奈·克莱门特"},
{"Irank": "273", "MovieName": "速度与激情7", "BoxOffice": "0.0", "SumBoxOffice": "0.0", "Director": "温子仁", "Genre1": "动作", "Genre2": "惊悚", "Genre3": "犯罪", "CAST1": "范·迪塞尔", "CAST2": "保罗·沃克", "CAST3": "杰森·斯坦森", "CAST4": "米歇尔·罗德里格兹", "CAST5": "乔丹娜·布鲁斯特"},
{"Irank": "276", "MovieName": "圆梦巨人", "BoxOffice": "0.0", "SumBoxOffice": "0.0", "Director": "史蒂文·斯皮尔伯格", "Genre1": "奇幻", "Genre2": "冒险", "Genre3": "-", "CAST1": "鲁比·巴恩希尔", "CAST2": "马克·里朗斯", "CAST3": "比尔·哈德尔", "CAST4": "丽贝卡·豪尔", "CAST5": "拉菲·斯波"},
{"Irank": "277", "MovieName": "大闹天竺", "BoxOffice": "0.0", "SumBoxOffice": "0.0", "Director": "王宝强", "Genre1": "喜剧", "Genre2": "动作", "Genre3": "冒险", "CAST1": "王宝强", "CAST2": "白客", "CAST3": "岳云鹏", "CAST4": "柳岩", "CAST5": "黄渤"},
{"Irank": "278", "MovieName": "生化危机：终章", "BoxOffice": "0.0", "SumBoxOffice": "0.0", "Director": "保罗·安德森", "Genre1": "动作", "Genre2": "科幻", "Genre3": "恐怖", "CAST1": "米拉·乔沃维奇", "CAST2": "伊恩·格雷", "CAST3": "艾丽·拉特", "CAST4": "鲁比·罗丝", "CAST5": "李准基"},
{"Irank": "279", "MovieName": "情遇曼哈顿", "BoxOffice": "0.0", "SumBoxOffice": "0.0", "Director": "李巨源", "Genre1": "喜剧", "Genre2": "爱情", "Genre3": "-", "CAST1": "王丽坤", "CAST2": "高以翔", "CAST3": "李媛", "CAST4": "王传君", "CAST5": "-"},
{"Irank": "280", "MovieName": "奇异博士", "BoxOffice": "0.0", "SumBoxOffice": "0.0", "Director": "斯科特·德瑞克森", "Genre1": "动作", "Genre2": "奇幻", "Genre3": "冒险", "CAST1": "本尼迪克特·康伯巴奇", "CAST2": "蒂尔达·斯文顿", "CAST3": "麦斯·米科尔森", "CAST4": "切瓦特·埃加福特", "CAST5": "瑞秋·麦克亚当斯"},
{"Irank": "281", "MovieName": "你幸福我快乐", "BoxOffice": "0.0", "SumBoxOffice": "0.0", "Director": "郦虹", "Genre1": "剧情", "Genre2": "喜剧", "Genre3": "-", "CAST1": "焉栩嘉", "CAST2": "陈怡霏", "CAST3": "-", "CAST4": "-", "CAST5": "-"},
{"Irank": "285", "MovieName": "爱丽丝梦游仙境2：镜中奇遇记", "BoxOffice": "0.0", "SumBoxOffice": "0.0", "Director": "詹姆斯·博宾", "Genre1": "奇幻", "Genre2": "冒险", "Genre3": "-", "CAST1": "约翰尼·德普", "CAST2": "米娅·华希科沃斯卡", "CAST3": "海伦娜·伯翰·卡特", "CAST4": "安妮·海瑟薇", "CAST5": "萨莎·拜伦·科恩"},
{"Irank": "286", "MovieName": "海底总动员2：多莉去哪儿", "BoxOffice": "0.0", "SumBoxOffice": "0.0", "Director": "安德鲁·斯坦顿", "Genre1": "喜剧", "Genre2": "动画", "Genre3": "家庭", "CAST1": "艾伦·德杰尼勒斯", "CAST2": "艾伯特·布鲁克斯", "CAST3": "艾德·奥尼尔", "CAST4": "凯特琳·奥尔森", "CAST5": "海登·罗兰斯"},
{"Irank": "287", "MovieName": "蝴蝶公墓", "BoxOffice": "0.0", "SumBoxOffice": "0.0", "Director": "马伟豪", "Genre1": "爱情", "Genre2": "奇幻", "Genre3": "-", "CAST1": "张俪", "CAST2": "锦荣", "CAST3": "李子峰", "CAST4": "李若彤", "CAST5": "安悦溪"},
{"Irank": "289", "MovieName": "功夫熊猫3", "BoxOffice": "0.0", "SumBoxOffice": "0.0", "Director": "吕寅荣", "Genre1": "喜剧", "Genre2": "动作", "Genre3": "动画", "CAST1": "杰克·布莱克", "CAST2": "布莱恩·科兰斯顿", "CAST3": "达斯汀·霍夫曼", "CAST4": "安吉丽娜·朱莉", "CAST5": "J·K·西蒙斯"},
{"Irank": "290", "MovieName": "鲁滨逊漂流记", "BoxOffice": "0.0", "SumBoxOffice": "0.0", "Director": "文森特·凯斯特鲁特", "Genre1": "喜剧", "Genre2": "动画", "Genre3": "冒险", "CAST1": "马提亚斯·施维赫夫", "CAST2": "卡亚·叶娜尔", "CAST3": "伊尔卡·贝桑", "CAST4": "迪特·哈勒沃登", "CAST5": "艾琳·特策尔"},
{"Irank": "294", "MovieName": "帕丁顿熊", "BoxOffice": "0.0", "SumBoxOffice": "0.0", "Director": "保罗·金", "Genre1": "喜剧", "Genre2": "动画", "Genre3": "家庭", "CAST1": "本·卫肖", "CAST2": "妮可·基德曼", "CAST3": "休·博纳维尔", "CAST4": "莎莉·霍金斯", "CAST5": "萨缪尔·乔斯林"},
{"Irank": "295", "MovieName": "人在驴途", "BoxOffice": "0.0", "SumBoxOffice": "0.0", "Director": "杨琳", "Genre1": "喜剧", "Genre2": "-", "Genre3": "-", "CAST1": "邵峰", "CAST2": "张亚光", "CAST3": "黄成麟", "CAST4": "李若嘉", "CAST5": "何苗"},
{"Irank": "296", "MovieName": "宽恕", "BoxOffice": "0.0", "SumBoxOffice": "0.0", "Director": "蒲剑", "Genre1": "剧情", "Genre2": "-", "Genre3": "-", "CAST1": "黄璐", "CAST2": "李立宏", "CAST3": "刘芳", "CAST4": "曹俊", "CAST5": "-"},
{"Irank": "297", "MovieName": "男神抱抱", "BoxOffice": "0.0", "SumBoxOffice": "0.0", "Director": "李小军", "Genre1": "剧情", "Genre2": "爱情", "Genre3": "-", "CAST1": "侯天悦", "CAST2": "荣梓希", "CAST3": "杨彤", "CAST4": "史元庭", "CAST5": "刘伟"},
{"Irank": "298", "MovieName": "致青春·原来你还在这里", "BoxOffice": "0.0", "SumBoxOffice": "0.0", "Director": "周拓如", "Genre1": "剧情", "Genre2": "爱情", "Genre3": "-", "CAST1": "吴亦凡", "CAST2": "刘亦菲", "CAST3": "金世佳", "CAST4": "李沁", "CAST5": "李梦"},
{"Irank": "299", "MovieName": "泡菜爱上小龙虾", "BoxOffice": "0.0", "SumBoxOffice": "0.0", "Director": "虞军豪", "Genre1": "喜剧", "Genre2": "奇幻", "Genre3": "-", "CAST1": "金起范", "CAST2": "徐申东", "CAST3": "元华", "CAST4": "陈德容", "CAST5": "苑琼丹"},
{"Irank": "301", "MovieName": "伊阿索密码", "BoxOffice": "0.0", "SumBoxOffice": "0.0", "Director": "李伟", "Genre1": "科幻", "Genre2": "悬疑", "Genre3": "惊悚", "CAST1": "梁静", "CAST2": "赵立新", "CAST3": "李兰迪", "CAST4": "王佳佳", "CAST5": "周明汕"},
{"Irank": "302", "MovieName": "52赫兹，我爱你", "BoxOffice": "0.0", "SumBoxOffice": "0.0", "Director": "魏德圣", "Genre1": "喜剧", "Genre2": "爱情", "Genre3": "歌舞", "CAST1": "庄鹃瑛", "CAST2": "林忠谕", "CAST3": "姜圣民", "CAST4": "陈玫希", "CAST5": "张榕容"},
{"Irank": "303", "MovieName": "龙珠Z：复活的弗利萨", "BoxOffice": "0.0", "SumBoxOffice": "0.0", "Director": "山室直儀", "Genre1": "动画", "Genre2": "-", "Genre3": "-", "CAST1": "野泽雅子", "CAST2": "中尾隆圣", "CAST3": "山寺宏一", "CAST4": "森田成一", "CAST5": "堀川亮"},
{"Irank": "308", "MovieName": "疯狂旅程", "BoxOffice": "0.0", "SumBoxOffice": "0.0", "Director": "龙野", "Genre1": "剧情", "Genre2": "喜剧", "Genre3": "-", "CAST1": "刘亮", "CAST2": "白鸽", "CAST3": "陆进", "CAST4": "关思慧", "CAST5": "徐广明"},
{"Irank": "309", "MovieName": "中国推销员", "BoxOffice": "0.0", "SumBoxOffice": "0.0", "Director": "檀冰", "Genre1": "剧情", "Genre2": "动作", "Genre3": "爱情", "CAST1": "李东学", "CAST2": "迈克·泰森", "CAST3": "史蒂文·席格", "CAST4": "李艾", "CAST5": "王自健"},
{"Irank": "312", "MovieName": "奔跑吧！兄弟", "BoxOffice": "0.0", "SumBoxOffice": "0.0", "Director": "胡笳", "Genre1": "喜剧", "Genre2": "-", "Genre3": "-", "CAST1": "杨颖", "CAST2": "王宝强", "CAST3": "李晨", "CAST4": "陈赫", "CAST5": "郑恺"},
{"Irank": "313", "MovieName": "异种", "BoxOffice": "0.0", "SumBoxOffice": "0.0", "Director": "过华", "Genre1": "悬疑", "Genre2": "惊悚", "Genre3": "恐怖", "CAST1": "刘青", "CAST2": "周浩东", "CAST3": "吴妍妍", "CAST4": "赵千紫", "CAST5": "于子健"},
{"Irank": "314", "MovieName": "大鱼海棠", "BoxOffice": "0.0", "SumBoxOffice": "0.0", "Director": "梁旋", "Genre1": "剧情", "Genre2": "动画", "Genre3": "奇幻", "CAST1": "季冠霖", "CAST2": "苏尚卿", "CAST3": "许魏洲", "CAST4": "金士杰", "CAST5": "杨婷"},
{"Irank": "315", "MovieName": "我的战争", "BoxOffice": "0.0", "SumBoxOffice": "0.0", "Director": "彭顺", "Genre1": "剧情", "Genre2": "历史", "Genre3": "战争", "CAST1": "刘烨", "CAST2": "王珞丹", "CAST3": "杨祐宁", "CAST4": "叶青", "CAST5": "黄志忠"},
{"Irank": "316", "MovieName": "三城记", "BoxOffice": "0.0", "SumBoxOffice": "0.0", "Director": "张婉婷", "Genre1": "剧情", "Genre2": "爱情", "Genre3": "-", "CAST1": "刘青云", "CAST2": "汤唯", "CAST3": "秦海璐", "CAST4": "井柏然", "CAST5": "黄觉"},
{"Irank": "317", "MovieName": "恶棍天使", "BoxOffice": "0.0", "SumBoxOffice": "0.0", "Director": "俞白眉", "Genre1": "喜剧", "Genre2": "-", "Genre3": "-", "CAST1": "邓超", "CAST2": "孙俪", "CAST3": "代乐乐", "CAST4": "梁超", "CAST5": "杨新鸣"},
{"Irank": "318", "MovieName": "血伞凶灵", "BoxOffice": "0.0", "SumBoxOffice": "0.0", "Director": "朱林森", "Genre1": "爱情", "Genre2": "惊悚", "Genre3": "-", "CAST1": "刘晓婉", "CAST2": "文卓", "CAST3": "朱佳希", "CAST4": "李炳渊", "CAST5": "初俊辰"},
{"Irank": "319", "MovieName": "蜡笔小新：梦境世界大突击", "BoxOffice": "0.0", "SumBoxOffice": "0.0", "Director": "高桥涉", "Genre1": "喜剧", "Genre2": "动画", "Genre3": "-", "CAST1": "矢岛晶子", "CAST2": "楢桥美纪", "CAST3": "藤原启治", "CAST4": "兴梠里美", "CAST5": "-"},
{"Irank": "321", "MovieName": "变形金刚5：最后的骑士", "BoxOffice": "0.0", "SumBoxOffice": "0.0", "Director": "迈克尔·贝", "Genre1": "动作", "Genre2": "科幻", "Genre3": "-", "CAST1": "马克·沃尔伯格", "CAST2": "伊莎贝拉·莫奈", "CAST3": "劳拉·哈德克", "CAST4": "安东尼·霍普金斯", "CAST5": "乔什·杜哈明"},
{"Irank": "323", "MovieName": "猩球崛起3：终极之战", "BoxOffice": "0.0", "SumBoxOffice": "0.0", "Director": "马特·里夫斯", "Genre1": "剧情", "Genre2": "动作", "Genre3": "科幻", "CAST1": "安迪·瑟金斯", "CAST2": "伍迪·哈里森", "CAST3": "史蒂夫·茨恩", "CAST4": "卡琳·考诺娃", "CAST5": "阿米尔·米勒"},
{"Irank": "325", "MovieName": "我只要我们在一起", "BoxOffice": "0.0", "SumBoxOffice": "0.0", "Director": "晏菲", "Genre1": "爱情", "Genre2": "-", "Genre3": "-", "CAST1": "杨恭如", "CAST2": "唐文龙", "CAST3": "迟帅", "CAST4": "周岭南", "CAST5": "-"},
{"Irank": "326", "MovieName": "我的个神啊", "BoxOffice": "0.0", "SumBoxOffice": "0.0", "Director": "拉吉库马尔·希拉尼", "Genre1": "喜剧", "Genre2": "奇幻", "Genre3": "-", "CAST1": "阿米尔·汗", "CAST2": "安努舒卡·莎玛", "CAST3": "桑杰·达特", "CAST4": "博曼·伊拉尼", "CAST5": "沙鲁巴·舒克拉"},
{"Irank": "327", "MovieName": "捉妖记", "BoxOffice": "0.0", "SumBoxOffice": "0.0", "Director": "许诚毅", "Genre1": "喜剧", "Genre2": "奇幻", "Genre3": "古装", "CAST1": "白百何", "CAST2": "井柏然", "CAST3": "姜武", "CAST4": "金燕玲", "CAST5": "钟汉良"},
{"Irank": "328", "MovieName": "西游记之孙悟空三打白骨精", "BoxOffice": "0.0", "SumBoxOffice": "0.0", "Director": "郑保瑞", "Genre1": "喜剧", "Genre2": "动作", "Genre3": "奇幻", "CAST1": "郭富城", "CAST2": "巩俐", "CAST3": "冯绍峰", "CAST4": "小沈阳", "CAST5": "罗仲谦"},
{"Irank": "329", "MovieName": "魔兽", "BoxOffice": "0.0", "SumBoxOffice": "0.0", "Director": "邓肯·琼斯", "Genre1": "动作", "Genre2": "奇幻", "Genre3": "冒险", "CAST1": "崔维斯·费米尔", "CAST2": "托比·凯贝尔", "CAST3": "宝拉·巴顿", "CAST4": "吴彦祖", "CAST5": "本·福斯特"},
{"Irank": "331", "MovieName": "大火种", "BoxOffice": "0.0", "SumBoxOffice": "0.0", "Director": "苗月", "Genre1": "剧情", "Genre2": "历史", "Genre3": "战争", "CAST1": "白威", "CAST2": "陈瑾", "CAST3": "王柠", "CAST4": "孙敏", "CAST5": "李超"},
{"Irank": "332", "MovieName": "冲上云霄", "BoxOffice": "0.0", "SumBoxOffice": "0.0", "Director": "叶伟信", "Genre1": "剧情", "Genre2": "爱情", "Genre3": "-", "CAST1": "古天乐", "CAST2": "郑秀文", "CAST3": "吴镇宇", "CAST4": "张智霖", "CAST5": "佘诗曼"},
{"Irank": "333", "MovieName": "一路惊喜", "BoxOffice": "0.0", "SumBoxOffice": "0.0", "Director": "金依萌", "Genre1": "喜剧", "Genre2": "爱情", "Genre3": "家庭", "CAST1": "郭采洁", "CAST2": "萧敬腾", "CAST3": "赵丽颖", "CAST4": "凤小岳", "CAST5": "夏雨"},
{"Irank": "335", "MovieName": "决不饶恕", "BoxOffice": "0.0", "SumBoxOffice": "0.0", "Director": "孙铁", "Genre1": "剧情", "Genre2": "-", "Genre3": "-", "CAST1": "巫刚", "CAST2": "刘斌", "CAST3": "节冰", "CAST4": "赵箩筐", "CAST5": "-"},
{"Irank": "337", "MovieName": "侏罗纪世界", "BoxOffice": "0.0", "SumBoxOffice": "0.0", "Director": "科林·特雷沃罗", "Genre1": "动作", "Genre2": "科幻", "Genre3": "冒险", "CAST1": "克里斯·帕拉特", "CAST2": "布莱丝·达拉斯·霍华德", "CAST3": "文森特·多诺费奥", "CAST4": "泰·辛普金斯", "CAST5": "尼克·罗宾森"},
{"Irank": "340", "MovieName": "六人晚餐", "BoxOffice": "0.0", "SumBoxOffice": "0.0", "Director": "李远", "Genre1": "剧情", "Genre2": "爱情", "Genre3": "-", "CAST1": "窦骁", "CAST2": "张钧甯", "CAST3": "邬君梅", "CAST4": "吴刚", "CAST5": "赵立新"},
{"Irank": "341", "MovieName": "我的特工爷爷", "BoxOffice": "0.0", "SumBoxOffice": "0.0", "Director": "洪金宝", "Genre1": "剧情", "Genre2": "动作", "Genre3": "冒险", "CAST1": "洪金宝", "CAST2": "刘德华", "CAST3": "朱雨辰", "CAST4": "李勤勤", "CAST5": "冯嘉怡"},
{"Irank": "342", "MovieName": "危城", "BoxOffice": "0.0", "SumBoxOffice": "0.0", "Director": "陈木胜", "Genre1": "剧情", "Genre2": "动作", "Genre3": "犯罪", "CAST1": "刘青云", "CAST2": "古天乐", "CAST3": "彭于晏", "CAST4": "吴京", "CAST5": "袁泉"},
{"Irank": "343", "MovieName": "李雷和韩梅梅", "BoxOffice": "0.0", "SumBoxOffice": "0.0", "Director": "杨永春", "Genre1": "剧情", "Genre2": "喜剧", "Genre3": "爱情", "CAST1": "张子枫", "CAST2": "张逸杰", "CAST3": "成梓宁", "CAST4": "李砚", "CAST5": "常铖"},
{"Irank": "344", "MovieName": "横冲直撞好莱坞", "BoxOffice": "0.0", "SumBoxOffice": "0.0", "Director": "蒂姆·肯德尔", "Genre1": "喜剧", "Genre2": "动作", "Genre3": "冒险", "CAST1": "赵薇", "CAST2": "黄晓明", "CAST3": "佟大为", "CAST4": "黎一墨", "CAST5": "姜成镐"},
{"Irank": "345", "MovieName": "精灵王座", "BoxOffice": "0.0", "SumBoxOffice": "0.0", "Director": "宋岳峰", "Genre1": "动画", "Genre2": "-", "Genre3": "-", "CAST1": "王梓", "CAST2": "陶典", "CAST3": "季冠霖", "CAST4": "黄莺", "CAST5": "-"},
{"Irank": "346", "MovieName": "少年师爷之大禹宝藏", "BoxOffice": "0.0", "SumBoxOffice": "0.0", "Director": "肖智慧", "Genre1": "喜剧", "Genre2": "动画", "Genre3": "-", "CAST1": "施野", "CAST2": "苏越越", "CAST3": "钱贯", "CAST4": "丁丁", "CAST5": "-"},
{"Irank": "347", "MovieName": "火影忍者剧场版：博人传", "BoxOffice": "0.0", "SumBoxOffice": "0.0", "Director": "山下宏幸", "Genre1": "动作", "Genre2": "动画", "Genre3": "冒险", "CAST1": "三瓶由布子", "CAST2": "菊池心", "CAST3": "竹内顺子", "CAST4": "杉山纪彰", "CAST5": "阿部敦"},
{"Irank": "348", "MovieName": "夏有乔木 雅望天堂", "BoxOffice": "0.0", "SumBoxOffice": "0.0", "Director": "赵真奎", "Genre1": "爱情", "Genre2": "-", "Genre3": "-", "CAST1": "吴亦凡", "CAST2": "韩庚", "CAST3": "卢杉", "CAST4": "包贝尔", "CAST5": "周元"},
{"Irank": "352", "MovieName": "大卫贝肯之倒霉特工熊", "BoxOffice": "0.0", "SumBoxOffice": "0.0", "Director": "李清舫", "Genre1": "喜剧", "Genre2": "动画", "Genre3": "家庭", "CAST1": "汤水雨", "CAST2": "徐佳琦", "CAST3": "杨默", "CAST4": "-", "CAST5": "-"},
{"Irank": "353", "MovieName": "三缺一", "BoxOffice": "0.0", "SumBoxOffice": "0.0", "Director": "高飞", "Genre1": "剧情", "Genre2": "爱情", "Genre3": "-", "CAST1": "谭卓", "CAST2": "葛兆美", "CAST3": "詹姆斯·奥夫斯", "CAST4": "李文俊", "CAST5": "-"},
{"Irank": "354", "MovieName": "从你的全世界路过", "BoxOffice": "0.0", "SumBoxOffice": "0.0", "Director": "张一白", "Genre1": "喜剧", "Genre2": "爱情", "Genre3": "-", "CAST1": "邓超", "CAST2": "白百何", "CAST3": "杨洋", "CAST4": "张天爱", "CAST5": "岳云鹏"},
{"Irank": "355", "MovieName": "相伴库里申科", "BoxOffice": "0.0", "SumBoxOffice": "0.0", "Director": "沈东", "Genre1": "剧情", "Genre2": "-", "Genre3": "-", "CAST1": "戴娇倩", "CAST2": "吴其江", "CAST3": "徐箭", "CAST4": "姜瑞佳", "CAST5": "宋春丽"},
{"Irank": "360", "MovieName": "仙球大战", "BoxOffice": "0.0", "SumBoxOffice": "0.0", "Director": "刘镇伟", "Genre1": "喜剧", "Genre2": "-", "Genre3": "-", "CAST1": "何炅", "CAST2": "钟欣潼", "CAST3": "蔡卓妍", "CAST4": "邓丽欣", "CAST5": "马丽"},
{"Irank": "361", "MovieName": "蓝精灵：寻找神秘村", "BoxOffice": "0.0", "SumBoxOffice": "0.0", "Director": "凯利·阿斯博瑞", "Genre1": "喜剧", "Genre2": "动画", "Genre3": "奇幻", "CAST1": "黛米·洛瓦托", "CAST2": "雷恩·威尔森", "CAST3": "乔·曼根尼罗", "CAST4": "杰克·麦克布瑞尔", "CAST5": "丹尼·朴迪"},
{"Irank": "364", "MovieName": "超能陆战队", "BoxOffice": "0.0", "SumBoxOffice": "0.0", "Director": "唐·霍尔", "Genre1": "喜剧", "Genre2": "动作", "Genre3": "科幻", "CAST1": "斯科特·安第斯", "CAST2": "瑞恩·波特", "CAST3": "丹尼尔·海尼", "CAST4": "T·J·米勒", "CAST5": "杰米·钟"},
{"Irank": "365", "MovieName": "寻龙诀", "BoxOffice": "0.0", "SumBoxOffice": "0.0", "Director": "乌尔善", "Genre1": "剧情", "Genre2": "动作", "Genre3": "奇幻", "CAST1": "陈坤", "CAST2": "黄渤", "CAST3": "舒淇", "CAST4": "杨颖", "CAST5": "夏雨"},
{"Irank": "366", "MovieName": "碟仙诡谭2", "BoxOffice": "0.0", "SumBoxOffice": "0.0", "Director": "雷宇扬", "Genre1": "悬疑", "Genre2": "惊悚", "Genre3": "-", "CAST1": "张韶涵", "CAST2": "方力申", "CAST3": "惠英红", "CAST4": "孙艺铭", "CAST5": "雷宇扬"},
{"Irank": "368", "MovieName": "复仇者联盟2：奥创纪元", "BoxOffice": "0.0", "SumBoxOffice": "0.0", "Director": "乔斯·韦登", "Genre1": "动作", "Genre2": "科幻", "Genre3": "奇幻", "CAST1": "小罗伯特·唐尼", "CAST2": "克里斯·海姆斯沃斯", "CAST3": "马克·鲁弗洛", "CAST4": "克里斯·埃文斯", "CAST5": "斯嘉丽·约翰逊"},
{"Irank": "369", "MovieName": "潜艇总动员5：时光宝盒", "BoxOffice": "0.0", "SumBoxOffice": "0.0", "Director": "何子力", "Genre1": "动画", "Genre2": "冒险", "Genre3": "-", "CAST1": "范楚绒", "CAST2": "洪海天", "CAST3": "谢元真", "CAST4": "王燕华", "CAST5": "谭满堂"},
{"Irank": "370", "MovieName": "雄狮", "BoxOffice": "0.0", "SumBoxOffice": "0.0", "Director": "加斯·戴维斯", "Genre1": "剧情", "Genre2": "-", "Genre3": "-", "CAST1": "戴夫·帕特尔", "CAST2": "鲁妮·玛拉", "CAST3": "大卫·文翰", "CAST4": "妮可·基德曼", "CAST5": "桑尼·帕沃"},
{"Irank": "371", "MovieName": "泡芙小姐", "BoxOffice": "0.0", "SumBoxOffice": "0.0", "Director": "张歆艺", "Genre1": "剧情", "Genre2": "爱情", "Genre3": "-", "CAST1": "张歆艺", "CAST2": "王栎鑫", "CAST3": "谭维维", "CAST4": "陈哲远", "CAST5": "于莎莎"},
{"Irank": "373", "MovieName": "我的少女时代", "BoxOffice": "0.0", "SumBoxOffice": "0.0", "Director": "陈玉珊", "Genre1": "喜剧", "Genre2": "爱情", "Genre3": "-", "CAST1": "宋芸桦", "CAST2": "王大陆", "CAST3": "李玉玺", "CAST4": "简廷芮", "CAST5": "刘德华"},
{"Irank": "374", "MovieName": "神兽金刚之青龙再现", "BoxOffice": "0.0", "SumBoxOffice": "0.0", "Director": "朱晓兵", "Genre1": "动画", "Genre2": "奇幻", "Genre3": "冒险", "CAST1": "黄健", "CAST2": "李仲鑫", "CAST3": "谢安晟", "CAST4": "泽飞", "CAST5": "陈蔡瑜"},
{"Irank": "377", "MovieName": "古曼", "BoxOffice": "0.0", "SumBoxOffice": "0.0", "Director": "张江南", "Genre1": "惊悚", "Genre2": "-", "Genre3": "-", "CAST1": "韩雪", "CAST2": "唐宸禹", "CAST3": "朱圣祎", "CAST4": "张翔", "CAST5": "张子蕾"},
{"Irank": "378", "MovieName": "新大头儿子和小头爸爸2一日成才", "BoxOffice": "0.0", "SumBoxOffice": "0.0", "Director": "何澄", "Genre1": "喜剧", "Genre2": "动画", "Genre3": "家庭", "CAST1": "刘纯燕", "CAST2": "董浩", "CAST3": "鞠萍", "CAST4": "林永健", "CAST5": "林大竣"},
{"Irank": "379", "MovieName": "远亲", "BoxOffice": "0.0", "SumBoxOffice": "0.0", "Director": "余铁", "Genre1": "剧情", "Genre2": "-", "Genre3": "-", "CAST1": "王伟", "CAST2": "兰婷", "CAST3": "黄静宜", "CAST4": "-", "CAST5": "-"},
{"Irank": "380", "MovieName": "恐怖笔记", "BoxOffice": "0.0", "SumBoxOffice": "0.0", "Director": "闵晋涛", "Genre1": "悬疑", "Genre2": "恐怖", "Genre3": "-", "CAST1": "赵泳鑫", "CAST2": "檀健次", "CAST3": "冯家妹", "CAST4": "潘春春", "CAST5": "-"},
{"Irank": "381", "MovieName": "冰川时代5：星际碰撞", "BoxOffice": "0.0", "SumBoxOffice": "0.0", "Director": "麦克·特米尔", "Genre1": "喜剧", "Genre2": "动画", "Genre3": "冒险", "CAST1": "西蒙·佩吉", "CAST2": "洁茜J", "CAST3": "杰西·泰勒·弗格森", "CAST4": "克里斯·韦奇", "CAST5": "詹妮弗·洛佩兹"},
{"Irank": "383", "MovieName": "哆啦A梦：大雄的南极冰冰凉大冒险", "BoxOffice": "0.0", "SumBoxOffice": "0.0", "Director": "高桥敦史", "Genre1": "动画", "Genre2": "冒险", "Genre3": "-", "CAST1": "水田山葵", "CAST2": "大原惠美", "CAST3": "嘉数由美", "CAST4": "木村昴", "CAST5": "关智一"},
{"Irank": "386", "MovieName": "美人鱼", "BoxOffice": "0.0", "SumBoxOffice": "0.0", "Director": "周星驰", "Genre1": "喜剧", "Genre2": "爱情", "Genre3": "奇幻", "CAST1": "邓超", "CAST2": "罗志祥", "CAST3": "张雨绮", "CAST4": "林允", "CAST5": "徐克"},
{"Irank": "388", "MovieName": "碟中谍5：神秘国度", "BoxOffice": "0.0", "SumBoxOffice": "0.0", "Director": "克里斯托弗·麦奎里", "Genre1": "动作", "Genre2": "惊悚", "Genre3": "冒险", "CAST1": "汤姆·克鲁斯", "CAST2": "杰瑞米·雷纳", "CAST3": "西蒙·佩吉", "CAST4": "丽贝卡·弗格森", "CAST5": "文·瑞姆斯"},
{"Irank": "389", "MovieName": "坏蛋必须死", "BoxOffice": "0.0", "SumBoxOffice": "0.0", "Director": "孙皓", "Genre1": "喜剧", "Genre2": "动作", "Genre3": "悬疑", "CAST1": "陈柏霖", "CAST2": "孙艺珍", "CAST3": "乔振宇", "CAST4": "申贤俊", "CAST5": "张光"},
{"Irank": "390", "MovieName": "不败雄心", "BoxOffice": "0.0", "SumBoxOffice": "0.0", "Director": "李冯", "Genre1": "剧情", "Genre2": "动作", "Genre3": "-", "CAST1": "付辛博", "CAST2": "熊乃瑾", "CAST3": "刘承俊", "CAST4": "-", "CAST5": "-"},
{"Irank": "391", "MovieName": "绝地逃亡", "BoxOffice": "0.0", "SumBoxOffice": "0.0", "Director": "雷尼·哈林", "Genre1": "喜剧", "Genre2": "动作", "Genre3": "-", "CAST1": "成龙", "CAST2": "范冰冰", "CAST3": "约翰尼·诺克斯维尔", "CAST4": "曾志伟", "CAST5": "王敏德"},
{"Irank": "392", "MovieName": "一条狗的使命", "BoxOffice": "0.0", "SumBoxOffice": "0.0", "Director": "拉斯·霍尔斯道姆", "Genre1": "剧情", "Genre2": "喜剧", "Genre3": "家庭", "CAST1": "乔什·加德", "CAST2": "布丽特·罗伯森", "CAST3": "丹尼斯·奎德", "CAST4": "佩吉·利普顿", "CAST5": "K·J·阿帕"},
{"Irank": "393", "MovieName": "记忆大师", "BoxOffice": "0.0", "SumBoxOffice": "0.0", "Director": "陈正道", "Genre1": "剧情", "Genre2": "悬疑", "Genre3": "惊悚", "CAST1": "黄渤", "CAST2": "段奕宏", "CAST3": "徐静蕾", "CAST4": "杨子姗", "CAST5": "梁杰理"},
{"Irank": "400", "MovieName": "麦兜·饭宝奇兵", "BoxOffice": "0.0", "SumBoxOffice": "0.0", "Director": "谢立文", "Genre1": "喜剧", "Genre2": "动画", "Genre3": "冒险", "CAST1": "金刚", "CAST2": "大汪", "CAST3": "张正中", "CAST4": "彭博", "CAST5": "孙小妞"},
{"Irank": "401", "MovieName": "杜鹃花红", "BoxOffice": "0.0", "SumBoxOffice": "0.0", "Director": "周盅光", "Genre1": "剧情", "Genre2": "-", "Genre3": "-", "CAST1": "由立平", "CAST2": "兰昊宇", "CAST3": "胡宗元", "CAST4": "王小伟", "CAST5": "陈瑞生"},
{"Irank": "403", "MovieName": "老炮儿", "BoxOffice": "0.0", "SumBoxOffice": "0.0", "Director": "管虎", "Genre1": "剧情", "Genre2": "犯罪", "Genre3": "-", "CAST1": "冯小刚", "CAST2": "许晴", "CAST3": "张涵予", "CAST4": "刘桦", "CAST5": "李易峰"},
{"Irank": "406", "MovieName": "爱宠大机密", "BoxOffice": "0.0", "SumBoxOffice": "0.0", "Director": "克里斯·雷纳德", "Genre1": "喜剧", "Genre2": "动画", "Genre3": "-", "CAST1": "路易·C·K", "CAST2": "艾瑞克·斯通斯崔特", "CAST3": "凯文·哈特", "CAST4": "艾丽·坎伯尔", "CAST5": "史蒂夫·库根"},
{"Irank": "407", "MovieName": "长城", "BoxOffice": "0.0", "SumBoxOffice": "0.0", "Director": "张艺谋", "Genre1": "动作", "Genre2": "奇幻", "Genre3": "冒险", "CAST1": "马特·达蒙", "CAST2": "景甜", "CAST3": "佩德罗·帕斯卡", "CAST4": "刘德华", "CAST5": "威廉·达福"},
{"Irank": "409", "MovieName": "铁笼", "BoxOffice": "0.0", "SumBoxOffice": "0.0", "Director": "徐捷", "Genre1": "剧情", "Genre2": "悬疑", "Genre3": "-", "CAST1": "徐捷", "CAST2": "冯伟力", "CAST3": "景涛", "CAST4": "文铭", "CAST5": "郭谯"},
{"Irank": "410", "MovieName": "龙拳小子", "BoxOffice": "0.0", "SumBoxOffice": "0.0", "Director": "陶声", "Genre1": "喜剧", "Genre2": "动作", "Genre3": "-", "CAST1": "刘芮麟", "CAST2": "林秋楠", "CAST3": "童菲", "CAST4": "梁超", "CAST5": "吴永伦"},
{"Irank": "411", "MovieName": "逗鸟外传：萌宝满天飞", "BoxOffice": "0.0", "SumBoxOffice": "0.0", "Director": "尼古拉斯·斯托勒", "Genre1": "喜剧", "Genre2": "动画", "Genre3": "奇幻", "CAST1": "安迪·萨姆伯格", "CAST2": "凯蒂·克朗", "CAST3": "凯尔希·格兰莫", "CAST4": "詹妮弗·安妮斯顿", "CAST5": "泰·布利尔"},
{"Irank": "412", "MovieName": "火锅英雄", "BoxOffice": "0.0", "SumBoxOffice": "0.0", "Director": "杨庆", "Genre1": "剧情", "Genre2": "犯罪", "Genre3": "-", "CAST1": "陈坤", "CAST2": "白百何", "CAST3": "秦昊", "CAST4": "喻恩泰", "CAST5": "王彦霖"},
{"Irank": "413", "MovieName": "小黄人大眼萌", "BoxOffice": "0.0", "SumBoxOffice": "0.0", "Director": "凯尔·巴尔达", "Genre1": "喜剧", "Genre2": "动画", "Genre3": "-", "CAST1": "桑德拉·布洛克", "CAST2": "乔恩·哈姆", "CAST3": "迈克尔·基顿", "CAST4": "艾莉森·珍妮", "CAST5": "史蒂夫·库根"},
{"Irank": "415", "MovieName": "超级快递", "BoxOffice": "0.0", "SumBoxOffice": "0.0", "Director": "宋啸", "Genre1": "喜剧", "Genre2": "动作", "Genre3": "-", "CAST1": "陈赫", "CAST2": "宋智孝", "CAST3": "大卫·贝利", "CAST4": "肖央", "CAST5": "李媛"}
]
}